pytrendy/__init__.py
pytrendy/detect_trends.py
pytrendy/io/__init__.py
pytrendy/io/data/classes_signals.csv
pytrendy/io/data/series_synthetic.csv
pytrendy/io/data_loader.py
pytrendy/io/plot_pytrendy.py
pytrendy/io/results_pytrendy.py
pytrendy/post_processing/__init__.py
pytrendy/post_processing/segments_analyse.py
pytrendy/post_processing/segments_get.py
pytrendy/post_processing/segments_refine/__init__.py
pytrendy/post_processing/segments_refine/abrupt_shaving.py
pytrendy/post_processing/segments_refine/artifact_cleanup.py
pytrendy/post_processing/segments_refine/gradual_expand_contract.py
pytrendy/post_processing/segments_refine/segment_grouping.py
pytrendy/post_processing/segments_refine/trend_classify.py
pytrendy/post_processing/segments_refine/update_neighbours.py
pytrendy/process_signals.py
pytrendy/simpledtw.py
pytrendy-1.1.8.dist-info/METADATA
pytrendy-1.1.8.dist-info/WHEEL
pytrendy-1.1.8.dist-info/licenses/LICENSE
pytrendy-1.1.8.dist-info/RECORD
