Metadata-Version: 2.4
Name: pytrendy
Version: 1.1.8
Summary: Trend Detection in Python. Applicable for real-world industry use cases in time series.
License: MIT License
License-File: LICENSE
Author: Russell Sammut Bonnici
Author-email: r.sammutbonnici@gmail.com
Maintainer: Russell Sammut Bonnici
Maintainer-email: r.sammutbonnici@gmail.com
Requires-Python: >=3.10
Classifier: License :: Other/Proprietary License
Classifier: Programming Language :: Python :: 3
Classifier: Programming Language :: Python :: 3.10
Classifier: Programming Language :: Python :: 3.11
Classifier: Programming Language :: Python :: 3.12
Classifier: Programming Language :: Python :: 3.13
Classifier: Programming Language :: Python :: 3.14
Requires-Dist: matplotlib
Requires-Dist: numpy
Requires-Dist: pandas
Requires-Dist: scipy
Project-URL: Repository, https://github.com/RussellSB/pytrendy
